setup.py
consistent_hash/__init__.py
consistent_hash/consistent_hash.py
consistent_hash_git.egg-info/PKG-INFO
consistent_hash_git.egg-info/SOURCES.txt
consistent_hash_git.egg-info/dependency_links.txt
consistent_hash_git.egg-info/top_level.txt