Metadata-Version: 1.0
Name: consistent-hash-git
Version: 0.3
Summary: Implements consistent hashing with Python.
Home-page: https://github.com/yummybian
Author: Yummy Bian
Author-email: yummy.bian@gmail.com
License: BSD
Keywords: consistent hash hashing
Platform: Any
